README.md
setup.cfg
setup.py
stationhead/__init__.py
stationhead/async_client.py
stationhead/client.py
stationhead.egg-info/PKG-INFO
stationhead.egg-info/SOURCES.txt
stationhead.egg-info/dependency_links.txt
stationhead.egg-info/requires.txt
stationhead.egg-info/top_level.txt
stationhead/utils/__init__.py
stationhead/utils/exceptions.py
stationhead/utils/objects.py
stationhead/utils/requester.py