Metadata-Version: 2.1
Name: stationhead
Version: 1.1
Summary: Library for creating stationhead bots and scripts.
Home-page: https://github.com/xXxCLOTIxXx/stationhead
Author: Xsarz
Author-email: xsarzy@gmail.com
License: MIT
Download-URL: https://github.com/xXxCLOTIxXx/stationhead/archive/refs/heads/main.zip
Keywords: stationhead.py,stationhead,stationhead-py,stationhead-bot,api,python,python3,python3.x,xsarz,official,sync
Platform: UNKNOWN
